dedict/__init__.py
dedict/interface.py
dedict/optional_attribute.py
dedict-1.0.7.dist-info/LICENSE
dedict-1.0.7.dist-info/METADATA
dedict-1.0.7.dist-info/WHEEL
dedict-1.0.7.dist-info/top_level.txt
dedict-1.0.7.dist-info/RECORD
