Metadata-Version: 2.1
Name: dedict
Version: 1.0.7
Summary: simple library to create objects from dictionaries
Home-page: UNKNOWN
Author: Olivier Verville
License: UNKNOWN
Platform: UNKNOWN
Classifier: Programming Language :: Python :: 3 :: Only
Classifier: Programming Language :: Python :: 3.6
Classifier: Programming Language :: Python :: 3.7
